py2proto/__init__.py
py2proto/main.py
py2proto-2.3.1.dist-info/LICENSE
py2proto-2.3.1.dist-info/METADATA
py2proto-2.3.1.dist-info/WHEEL
py2proto-2.3.1.dist-info/top_level.txt
py2proto-2.3.1.dist-info/RECORD
