Metadata-Version: 2.1
Name: py2proto
Version: 2.3.1
Summary: An ORM-like Python library for generating and managing gRPC proto files and pb2 files
Author-email: Mahdi Ghasemi <mahdighasemiabari@gmail.com>
License: Copyright (c) 2024 The Python Packaging Authority
Project-URL: Homepage, https://github.com/prodbygodfather/py2proto
Project-URL: Bug Tracker, https://github.com/prodbygodfather/py2proto/issues
Keywords: grpc,protobuf,code generation,protobuf ORM,auto create pb2 & proto file,py2proto
Classifier: Programming Language :: Python :: 3
Classifier: License :: OSI Approved :: MIT License
Classifier: Operating System :: OS Independent
Requires-Python: >=3.8
License-File: LICENSE
Requires-Dist: grpcio-tools >=1.30.0
Requires-Dist: grpcio >=1.30.0
Requires-Dist: Flask >=2.0.0
Requires-Dist: protobuf >=3.15.0
Requires-Dist: requests >=2.25.0
